sedfitter/__init__.py
sedfitter/extract_parameters.py
sedfitter/filter_output.py
sedfitter/fit.py
sedfitter/fit_info.py
sedfitter/fitting_routines.py
sedfitter/models.py
sedfitter/plot.py
sedfitter/plot_helpers.py
sedfitter/plot_params_1d.py
sedfitter/plot_params_2d.py
sedfitter/timer.py
sedfitter/version.py
sedfitter/write_parameter_ranges.py
sedfitter/write_parameters.py
sedfitter/convolve/__init__.py
sedfitter/convolve/convolve.py
sedfitter/convolve/monochromatic.py
sedfitter/convolved_fluxes/__init__.py
sedfitter/convolved_fluxes/convolved_fluxes.py
sedfitter/convolved_fluxes/tests/__init__.py
sedfitter/convolved_fluxes/tests/test_convolved_fluxes.py
sedfitter/extinction/__init__.py
sedfitter/extinction/extinction.py
sedfitter/extinction/tests/__init__.py
sedfitter/extinction/tests/test_extinction.py
sedfitter/filter/__init__.py
sedfitter/filter/filter.py
sedfitter/filter/tests/__init__.py
sedfitter/filter/tests/test_filter.py
sedfitter/filter/tests/data/2J.txt
sedfitter/filter/tests/data/I1.txt
sedfitter/filter/tests/data/S3.txt
sedfitter/sed/__init__.py
sedfitter/sed/cube.py
sedfitter/sed/helpers.py
sedfitter/sed/sed.py
sedfitter/sed/tests/__init__.py
sedfitter/sed/tests/test_cube.py
sedfitter/sed/tests/test_sed.py
sedfitter/sed/tests/data/3000030_1_sed.fits.gz
sedfitter/sed/tests/data/kt09250g+4.0z-0.5_sed.fits.gz
sedfitter/source/__init__.py
sedfitter/source/source.py
sedfitter/source/tests/__init__.py
sedfitter/source/tests/test_source.py
sedfitter/tests/__init__.py
sedfitter/tests/test_full_pipeline.py
sedfitter/utils/__init__.py
sedfitter/utils/formatter.py
sedfitter/utils/integrate.py
sedfitter/utils/interpolate.py
sedfitter/utils/io.py
sedfitter/utils/list2data.py
sedfitter/utils/misc.py
sedfitter/utils/parfile.py
sedfitter/utils/validator.py
sedfitter/utils/tests/__init__.py
sedfitter/utils/tests/test_parfile.py
sedfitter/utils/tests/data/test.conf
sedfitter/utils/tests/data/test.par
sedfitter-1.4.dist-info/METADATA
sedfitter-1.4.dist-info/WHEEL
sedfitter-1.4.dist-info/top_level.txt
sedfitter-1.4.dist-info/RECORD
