Metadata-Version: 2.1
Name: sedfitter
Version: 1.4
Summary: SED Fitter in Python
Home-page: https://github.com/astrofrog/sedfitter
Author: Thomas Robitaille
Author-email: thomas.robitaille@gmail.com
License: BSD 2-Clause
Requires-Python: >=3.8
Requires-Dist: numpy (>=1.18)
Requires-Dist: scipy (>=1.3)
Requires-Dist: matplotlib (>=3.1)
Requires-Dist: astropy (>=5.0)
Provides-Extra: docs
Requires-Dist: sphinx ; extra == 'docs'
Requires-Dist: sphinx-automodapi ; extra == 'docs'
Requires-Dist: numpydoc ; extra == 'docs'
Provides-Extra: test
Requires-Dist: pytest ; extra == 'test'
Requires-Dist: pytest-cov ; extra == 'test'
